{
  "size": 0.7,
  "maxLife": 30,
  "type": "std",
  "price": 100,
  "ability": {
    "type": "sloMo",
    "factor": 0.45,
    "rechargeTime": 5
  },
  "displayName": "Wyrm",
  "engine": "core:imperialEngine",
  "gunSlots": [
    {
      "position": "0.6 0.49625",
      "isUnderneathHull": true,
      "allowsRotation": false
    }
  ],
  "rigidBody":
  {
    "name": "draconicTinyBody",
    "imagePath": "DestinationSol/modules/draconic/assets/ships/draconicTiny/draconicTiny.png",
    "origin": {
      "x": 0.5,
      "y": 0.5
    },
    "polygons": [
      [
        {
          "x": 0.3359375,
          "y": 0.609375
        },
        {
          "x": 0.1953125,
          "y": 0.6484375
        },
        {
          "x": 0.1171875,
          "y": 0.5859375
        },
        {
          "x": 0.09375,
          "y": 0.5078125
        },
        {
          "x": 0.140625,
          "y": 0.40625
        },
        {
          "x": 0.203125,
          "y": 0.3671875
        },
        {
          "x": 0.34375,
          "y": 0.3984375
        }
      ],
      [
        {
          "x": 0.3828125,
          "y": 0.2890625
        },
        {
          "x": 0.34375,
          "y": 0.28125
        },
        {
          "x": 0.3828125,
          "y": 0.2578125
        },
        {
          "x": 0.5859375,
          "y": 0.2734375
        }
      ],
      [
        {
          "x": 0.5859375,
          "y": 0.2734375
        },
        {
          "x": 0.7578125,
          "y": 0.34375
        },
        {
          "x": 0.8474999666213989,
          "y": 0.42625001072883606
        },
        {
          "x": 0.7890625,
          "y": 0.453125
        },
        {
          "x": 0.6328125,
          "y": 0.4609375
        },
        {
          "x": 0.390625,
          "y": 0.3515625
        },
        {
          "x": 0.359375,
          "y": 0.3203125
        },
        {
          "x": 0.3828125,
          "y": 0.2890625
        }
      ],
      [
        {
          "x": 0.6328125,
          "y": 0.4609375
        },
        {
          "x": 0.625,
          "y": 0.5234375
        },
        {
          "x": 0.3828125,
          "y": 0.6484375
        },
        {
          "x": 0.3359375,
          "y": 0.609375
        },
        {
          "x": 0.34375,
          "y": 0.3984375
        },
        {
          "x": 0.390625,
          "y": 0.3515625
        }
      ],
      [
        {
          "x": 0.6640625,
          "y": 0.5625
        },
        {
          "x": 0.8450000286102295,
          "y": 0.5712500214576721
        },
        {
          "x": 0.7890625,
          "y": 0.6484375
        },
        {
          "x": 0.6796875,
          "y": 0.7109375
        }
      ],
      [
        {
          "x": 0.6796875,
          "y": 0.7109375
        },
        {
          "x": 0.4921875,
          "y": 0.7578125
        },
        {
          "x": 0.390625,
          "y": 0.7109375
        },
        {
          "x": 0.359375,
          "y": 0.6796875
        },
        {
          "x": 0.3828125,
          "y": 0.6484375
        },
        {
          "x": 0.625,
          "y": 0.5234375
        },
        {
          "x": 0.6640625,
          "y": 0.5625
        }
      ],
      [
        {
          "x": 0.4921875,
          "y": 0.7578125
        },
        {
          "x": 0.3359375,
          "y": 0.7578125
        },
        {
          "x": 0.3203125,
          "y": 0.7421875
        },
        {
          "x": 0.390625,
          "y": 0.7109375
        }
      ]
    ],
    "circles": [],
    "shapes": [
      {
        "type": "POLYGON",
        "vertices": [
          {
            "x": 0.3359375,
            "y": 0.7578125
          },
          {
            "x": 0.4921875,
            "y": 0.7578125
          },
          {
            "x": 0.6796875,
            "y": 0.7109375
          },
          {
            "x": 0.7890625,
            "y": 0.6484375
          },
          {
            "x": 0.8450000286102295,
            "y": 0.5712500214576721
          },
          {
            "x": 0.6640625,
            "y": 0.5625
          },
          {
            "x": 0.625,
            "y": 0.5234375
          },
          {
            "x": 0.6328125,
            "y": 0.4609375
          },
          {
            "x": 0.7890625,
            "y": 0.453125
          },
          {
            "x": 0.8474999666213989,
            "y": 0.42625001072883606
          },
          {
            "x": 0.7578125,
            "y": 0.34375
          },
          {
            "x": 0.5859375,
            "y": 0.2734375
          },
          {
            "x": 0.3828125,
            "y": 0.2578125
          },
          {
            "x": 0.34375,
            "y": 0.28125
          },
          {
            "x": 0.3828125,
            "y": 0.2890625
          },
          {
            "x": 0.359375,
            "y": 0.3203125
          },
          {
            "x": 0.390625,
            "y": 0.3515625
          },
          {
            "x": 0.34375,
            "y": 0.3984375
          },
          {
            "x": 0.203125,
            "y": 0.3671875
          },
          {
            "x": 0.140625,
            "y": 0.40625
          },
          {
            "x": 0.09375,
            "y": 0.5078125
          },
          {
            "x": 0.1171875,
            "y": 0.5859375
          },
          {
            "x": 0.1953125,
            "y": 0.6484375
          },
          {
            "x": 0.3359375,
            "y": 0.609375
          },
          {
            "x": 0.3828125,
            "y": 0.6484375
          },
          {
            "x": 0.359375,
            "y": 0.6796875
          },
          {
            "x": 0.390625,
            "y": 0.7109375
          },
          {
            "x": 0.3203125,
            "y": 0.7421875
          }
        ]
      }
    ]
  },
  "dynamicObjects": [],
  "particleEmitters": [
    {
      "position": "0.0703125 0.35546875",
      "trigger": "engine",
      "hasLight": true,
      "particle": {
        "effectFile": "core:flame",
        "size": 0.07,
        "tex": "core:fire",
        "tint": "hsb 140 20 65"
      },
      "workSounds": [
        "core:medEngineWork0",
        "core:medEngineWork1",
        "core:medEngineWork2",
        "core:medEngineWork3",
        "core:medEngineWork4"
      ]
    },
    {
      "position": "0.078125 0.62109375",
      "trigger": "engine",
      "hasLight": true,
      "particle": {
        "effectFile": "core:flame",
        "size": 0.07,
        "tex": "core:fire",
        "tint": "hsb 140 20 65"
      },
      "workSounds": [
        "core:medEngineWork0",
        "core:medEngineWork1",
        "core:medEngineWork2",
        "core:medEngineWork3",
        "core:medEngineWork4"
      ]
    }
  ]
}